MANIFEST.in
setup.cfg
setup.py
crawley/__init__.py
crawley/config.py
crawley/exceptions.py
crawley/extractors.py
crawley/bin/crawley
crawley/conf/templates/config.tm
crawley/conf/templates/crawlers.tm
crawley/conf/templates/html_template.tm
crawley/conf/templates/metadata.tm
crawley/conf/templates/models.tm
crawley/conf/templates/settings.tm
crawley/conf/templates/template.tm
crawley/crawlers/__init__.py
crawley/crawlers/base.py
crawley/crawlers/fast.py
crawley/crawlers/offline.py
crawley/http/__init__.py
crawley/http/cookies.py
crawley/http/managers.py
crawley/http/request.py
crawley/http/response.py
crawley/http/urls.py
crawley/manager/__init__.py
crawley/manager/utils.py
crawley/manager/commands/__init__.py
crawley/manager/commands/browser.py
crawley/manager/commands/command.py
crawley/manager/commands/migratedb.py
crawley/manager/commands/run.py
crawley/manager/commands/shell.py
crawley/manager/commands/startproject.py
crawley/manager/commands/syncdb.py
crawley/manager/projects/__init__.py
crawley/manager/projects/base.py
crawley/manager/projects/code.py
crawley/manager/projects/database.py
crawley/manager/projects/template.py
crawley/multiprogramming/__init__.py
crawley/multiprogramming/collections.py
crawley/multiprogramming/pool.py
crawley/multiprogramming/threads.py
crawley/persistance/__init__.py
crawley/persistance/documents/__init__.py
crawley/persistance/documents/csv_doc.py
crawley/persistance/documents/json_doc.py
crawley/persistance/documents/meta.py
crawley/persistance/documents/xml.py
crawley/persistance/nosql/__init__.py
crawley/persistance/nosql/base.py
crawley/persistance/nosql/couch.py
crawley/persistance/nosql/mongo.py
crawley/persistance/relational/__init__.py
crawley/persistance/relational/connectors.py
crawley/persistance/relational/databases.py
crawley/scrapers/__init__.py
crawley/scrapers/base.py
crawley/scrapers/smart.py
crawley/simple_parser/__init__.py
crawley/simple_parser/compilers.py
crawley/simple_parser/config_parser.py
crawley_dev.egg-info/PKG-INFO
crawley_dev.egg-info/SOURCES.txt
crawley_dev.egg-info/dependency_links.txt
crawley_dev.egg-info/requires.txt
crawley_dev.egg-info/top_level.txt
