Metadata-Version: 1.0
Name: crawley-dev
Version: 0.2.4
Summary: Pythonic Scraping / Crawling FrameWork built On Eventlet
Home-page: http://crawley-project.org/
Author: Crawley Developers
Author-email: jmg.utn@gmail.com
License: GPL v3
Keywords: Scraping Crawling Framework Python
Platform: UNKNOWN
